MoonIndex/__init__.py
MoonIndex/filtration.py
MoonIndex/indexes.py
MoonIndex/plotting.py
MoonIndex/preparation.py
moonindex-3.0.3.dist-info/licenses/LICENSE.txt
moonindex-3.0.3.dist-info/METADATA
moonindex-3.0.3.dist-info/WHEEL
moonindex-3.0.3.dist-info/top_level.txt
moonindex-3.0.3.dist-info/RECORD
